<?xml version="1.0" encoding="UTF-8"?>
<!DOCTYPE mapper PUBLIC "-//mybatis.org//DTD Mapper 3.0//EN" "http://mybatis.org/dtd/mybatis-3-mapper.dtd">
<mapper namespace="com.woniu.mapper.OwnershipMapper">
  <resultMap id="BaseResultMap" type="com.woniu.entity.Ownership">
    <!--
      WARNING - @mbg.generated
      This element is automatically generated by MyBatis Generator, do not modify.
      This element was generated on Wed Aug 21 14:57:48 CST 2019.
    -->
    <id column="osid" jdbcType="INTEGER" property="osid" />
    <result column="servicenumber" jdbcType="VARCHAR" property="servicenumber" />
    <result column="roomid" jdbcType="INTEGER" property="roomid" />
    <result column="registertime" jdbcType="TIMESTAMP" property="registertime" />
    <result column="uid" jdbcType="INTEGER" property="uid" />
    <result column="descript" jdbcType="VARCHAR" property="descript" />
    <result column="clientid" jdbcType="INTEGER" property="clientid" />
    <collection property="client" column="clientid" select="com.woniu.mapper.ClientMapper.selectByPrimaryKey"></collection>
  	<collection property="userinfo" column="uid" select="com.woniu.mapper.UserinfoMapper.selectByPrimaryKey"></collection>
  </resultMap>
  
   <resultMap type="com.woniu.entity.Ownership" id="BaseResultMapWithOther" extends="BaseResultMap">
  	  <association property="room" javaType="com.woniu.entity.Room">
		  <id column="roomid" jdbcType="INTEGER" property="roomid" />
		  <result column="roomnumber" jdbcType="VARCHAR" property="roomnumber" />
		  <result column="roomstatusid" jdbcType="INTEGER" property="roomstatusid" />
		  <result column="buildingid" jdbcType="INTEGER" property="buildingid" />
	  </association>
	  <association property="building" javaType="com.woniu.entity.Building">
  			<id column="buildingid" jdbcType="INTEGER" property="buildingid" />
		    <result column="buildingname" jdbcType="VARCHAR" property="buildingname" />
		    <result column="buildingnumber" jdbcType="VARCHAR" property="buildingnumber" />
		    <result column="floor" jdbcType="INTEGER" property="floor" />
		    <result column="count" jdbcType="INTEGER" property="count" />
		    <result column="totalarea" jdbcType="INTEGER" property="totalarea" />
		    <result column="descripe" jdbcType="VARCHAR" property="descripe" />
		    <result column="hid" jdbcType="INTEGER" property="hid" />
  		</association>
  		<association property="house" javaType="com.woniu.entity.House">
	  		<id column="hid" jdbcType="INTEGER" property="hid" />
		    <result column="hname" jdbcType="VARCHAR" property="hname" />
		    <result column="cid" jdbcType="INTEGER" property="cid" />
		    <result column="lid" jdbcType="INTEGER" property="lid" />
		    <result column="oid" jdbcType="INTEGER" property="oid" />
		    <result column="rid" jdbcType="INTEGER" property="rid" />
		    <result column="did" jdbcType="INTEGER" property="did" />
		    <result column="zid" jdbcType="INTEGER" property="zid" />
		    <result column="bid" jdbcType="INTEGER" property="bid" />
		    <result column="lnid" jdbcType="INTEGER" property="lnid" />
		    <result column="bsid" jdbcType="INTEGER" property="bsid" />
		    <result column="gid" jdbcType="INTEGER" property="gid" />
		    <result column="location" jdbcType="VARCHAR" property="location" />
		    <result column="housedrawing" jdbcType="VARCHAR" property="housedrawing" />
		    <result column="housestatusid" jdbcType="INTEGER" property="housestatusid" />
		    <result column="hdate" jdbcType="DATE" property="hdate" />
	  	</association>
	  	<association property="landnumber" javaType="com.woniu.entity.Landnumber">
	  		<id column="lnid" jdbcType="INTEGER" property="lnid" />
		    <result column="lnname" jdbcType="VARCHAR" property="lnname" />
		    <result column="bid" jdbcType="INTEGER" property="bid" />
	  	</association>
	  	<association property="userinfo" javaType="com.woniu.entity.Userinfo">
	  		<id column="uid" jdbcType="INTEGER" property="uid" />
		    <result column="uname" jdbcType="VARCHAR" property="uname" />
		    <result column="upass" jdbcType="VARCHAR" property="upass" />
		    <result column="isdelete" jdbcType="BIT" property="isdelete" />
		    <result column="indeptid" jdbcType="INTEGER" property="indeptid" />
	  	</association>
	  	<association property="client" javaType="com.woniu.entity.Client">
	  		 <id column="clientid" jdbcType="INTEGER" property="clientid" />
		    <result column="clientname" jdbcType="VARCHAR" property="clientname" />
		    <result column="address" jdbcType="VARCHAR" property="address" />
		    <result column="idcard" jdbcType="VARCHAR" property="idcard" />
		    <result column="phone" jdbcType="VARCHAR" property="phone" />
		    <result column="zid" jdbcType="INTEGER" property="zid" />
	  	</association>
  </resultMap>
  
  <select id="findByHid" resultMap="BaseResultMapWithOther">
  		select *
		from ownership o,client c,userinfo u,house h,landnumber l,room r,building b
		where o.roomid=r.roomid and r.buildingid=b.buildingid and b.hid=h.hid and h.lnid=l.lnid and o.clientid=c.clientid and o.uid=u.uid
		and h.hid=#{hid}
  </select>
  
  <select id="findByClientid" resultMap="BaseResultMapWithOther">
  		select *
		from ownership o,client c,userinfo u,house h,landnumber l,room r,building b
		where o.roomid=r.roomid and r.buildingid=b.buildingid and b.hid=h.hid and h.lnid=l.lnid and o.clientid=c.clientid and o.uid=u.uid
		and o.clientid=#{clientid}
  </select>
  
  <select id="findByServicenumber" resultMap="BaseResultMapWithOther">
  	    select *
		from ownership o,client c,userinfo u,house h,landnumber l,room r,building b
		where o.roomid=r.roomid and r.buildingid=b.buildingid and b.hid=h.hid and h.lnid=l.lnid and o.clientid=c.clientid and o.uid=u.uid
		and o.servicenumber=#{servicenumber}
  </select>
  
  <select id="countByBuyerid" resultType="java.lang.Integer">
  	SELECT COUNT(*) FROM ownership o WHERE EXISTS (
	SELECT servicenumber FROM service s WHERE s.proposer=#{buyerid} AND o.servicenumber=s.servicenumber AND s.servicetypeid=6 OR s.servicetypeid=7 OR s.servicetypeid=8

)
  </select>
  
  <select id="findByRoomId" resultMap="BaseResultMap">
  		select*from ownership where roomid=#{roomid}
  </select>
  
  <delete id="deleteByRoomid" parameterType="java.lang.Integer">
  		delete from ownership where roomid=#{roomid}
  </delete>
 
  <sql id="Example_Where_Clause">
    <!--
      WARNING - @mbg.generated
      This element is automatically generated by MyBatis Generator, do not modify.
      This element was generated on Wed Aug 21 14:57:48 CST 2019.
    -->
    <where>
      <foreach collection="oredCriteria" item="criteria" separator="or">
        <if test="criteria.valid">
          <trim prefix="(" prefixOverrides="and" suffix=")">
            <foreach collection="criteria.criteria" item="criterion">
              <choose>
                <when test="criterion.noValue">
                  and ${criterion.condition}
                </when>
                <when test="criterion.singleValue">
                  and ${criterion.condition} #{criterion.value}
                </when>
                <when test="criterion.betweenValue">
                  and ${criterion.condition} #{criterion.value} and #{criterion.secondValue}
                </when>
                <when test="criterion.listValue">
                  and ${criterion.condition}
                  <foreach close=")" collection="criterion.value" item="listItem" open="(" separator=",">
                    #{listItem}
                  </foreach>
                </when>
              </choose>
            </foreach>
          </trim>
        </if>
      </foreach>
    </where>
  </sql>
  <sql id="Update_By_Example_Where_Clause">
    <!--
      WARNING - @mbg.generated
      This element is automatically generated by MyBatis Generator, do not modify.
      This element was generated on Wed Aug 21 14:57:48 CST 2019.
    -->
    <where>
      <foreach collection="example.oredCriteria" item="criteria" separator="or">
        <if test="criteria.valid">
          <trim prefix="(" prefixOverrides="and" suffix=")">
            <foreach collection="criteria.criteria" item="criterion">
              <choose>
                <when test="criterion.noValue">
                  and ${criterion.condition}
                </when>
                <when test="criterion.singleValue">
                  and ${criterion.condition} #{criterion.value}
                </when>
                <when test="criterion.betweenValue">
                  and ${criterion.condition} #{criterion.value} and #{criterion.secondValue}
                </when>
                <when test="criterion.listValue">
                  and ${criterion.condition}
                  <foreach close=")" collection="criterion.value" item="listItem" open="(" separator=",">
                    #{listItem}
                  </foreach>
                </when>
              </choose>
            </foreach>
          </trim>
        </if>
      </foreach>
    </where>
  </sql>
  <sql id="Base_Column_List">
    <!--
      WARNING - @mbg.generated
      This element is automatically generated by MyBatis Generator, do not modify.
      This element was generated on Wed Aug 21 14:57:48 CST 2019.
    -->
    osid, servicenumber, roomid, registertime, uid, descript, clientid
  </sql>
  <select id="selectByExample" parameterType="com.woniu.entity.OwnershipExample" resultMap="BaseResultMap">
    <!--
      WARNING - @mbg.generated
      This element is automatically generated by MyBatis Generator, do not modify.
      This element was generated on Wed Aug 21 14:57:48 CST 2019.
    -->
    select
    <if test="distinct">
      distinct
    </if>
    <include refid="Base_Column_List" />
    from ownership
    <if test="_parameter != null">
      <include refid="Example_Where_Clause" />
    </if>
    <if test="orderByClause != null">
      order by ${orderByClause}
    </if>
  </select>
  <select id="selectByPrimaryKey" parameterType="java.lang.Integer" resultMap="BaseResultMap">
    <!--
      WARNING - @mbg.generated
      This element is automatically generated by MyBatis Generator, do not modify.
      This element was generated on Wed Aug 21 14:57:48 CST 2019.
    -->
    select 
    <include refid="Base_Column_List" />
    from ownership
    where osid = #{osid,jdbcType=INTEGER}
  </select>
  <delete id="deleteByPrimaryKey" parameterType="java.lang.Integer">
    <!--
      WARNING - @mbg.generated
      This element is automatically generated by MyBatis Generator, do not modify.
      This element was generated on Wed Aug 21 14:57:48 CST 2019.
    -->
    delete from ownership
    where osid = #{osid,jdbcType=INTEGER}
  </delete>
  <delete id="deleteByExample" parameterType="com.woniu.entity.OwnershipExample">
    <!--
      WARNING - @mbg.generated
      This element is automatically generated by MyBatis Generator, do not modify.
      This element was generated on Wed Aug 21 14:57:48 CST 2019.
    -->
    delete from ownership
    <if test="_parameter != null">
      <include refid="Example_Where_Clause" />
    </if>
  </delete>
  <insert id="insert" parameterType="com.woniu.entity.Ownership">
    <!--
      WARNING - @mbg.generated
      This element is automatically generated by MyBatis Generator, do not modify.
      This element was generated on Wed Aug 21 14:57:48 CST 2019.
    -->
    insert into ownership (osid, servicenumber, roomid, 
      registertime, uid, descript, 
      clientid)
    values (#{osid,jdbcType=INTEGER}, #{servicenumber,jdbcType=VARCHAR}, #{roomid,jdbcType=INTEGER}, 
      #{registertime,jdbcType=TIMESTAMP}, #{uid,jdbcType=INTEGER}, #{descript,jdbcType=VARCHAR}, 
      #{clientid,jdbcType=INTEGER})
  </insert>
  <insert id="insertSelective" parameterType="com.woniu.entity.Ownership">
    <!--
      WARNING - @mbg.generated
      This element is automatically generated by MyBatis Generator, do not modify.
      This element was generated on Wed Aug 21 14:57:48 CST 2019.
    -->
    insert into ownership
    <trim prefix="(" suffix=")" suffixOverrides=",">
      <if test="osid != null">
        osid,
      </if>
      <if test="servicenumber != null">
        servicenumber,
      </if>
      <if test="roomid != null">
        roomid,
      </if>
      <if test="registertime != null">
        registertime,
      </if>
      <if test="uid != null">
        uid,
      </if>
      <if test="descript != null">
        descript,
      </if>
      <if test="clientid != null">
        clientid,
      </if>
    </trim>
    <trim prefix="values (" suffix=")" suffixOverrides=",">
      <if test="osid != null">
        #{osid,jdbcType=INTEGER},
      </if>
      <if test="servicenumber != null">
        #{servicenumber,jdbcType=VARCHAR},
      </if>
      <if test="roomid != null">
        #{roomid,jdbcType=INTEGER},
      </if>
      <if test="registertime != null">
        #{registertime,jdbcType=TIMESTAMP},
      </if>
      <if test="uid != null">
        #{uid,jdbcType=INTEGER},
      </if>
      <if test="descript != null">
        #{descript,jdbcType=VARCHAR},
      </if>
      <if test="clientid != null">
        #{clientid,jdbcType=INTEGER},
      </if>
    </trim>
  </insert>
  <select id="countByExample" parameterType="com.woniu.entity.OwnershipExample" resultType="java.lang.Long">
    <!--
      WARNING - @mbg.generated
      This element is automatically generated by MyBatis Generator, do not modify.
      This element was generated on Wed Aug 21 14:57:48 CST 2019.
    -->
    select count(*) from ownership
    <if test="_parameter != null">
      <include refid="Example_Where_Clause" />
    </if>
  </select>
  <update id="updateByExampleSelective" parameterType="map">
    <!--
      WARNING - @mbg.generated
      This element is automatically generated by MyBatis Generator, do not modify.
      This element was generated on Wed Aug 21 14:57:48 CST 2019.
    -->
    update ownership
    <set>
      <if test="record.osid != null">
        osid = #{record.osid,jdbcType=INTEGER},
      </if>
      <if test="record.servicenumber != null">
        servicenumber = #{record.servicenumber,jdbcType=VARCHAR},
      </if>
      <if test="record.roomid != null">
        roomid = #{record.roomid,jdbcType=INTEGER},
      </if>
      <if test="record.registertime != null">
        registertime = #{record.registertime,jdbcType=TIMESTAMP},
      </if>
      <if test="record.uid != null">
        uid = #{record.uid,jdbcType=INTEGER},
      </if>
      <if test="record.descript != null">
        descript = #{record.descript,jdbcType=VARCHAR},
      </if>
      <if test="record.clientid != null">
        clientid = #{record.clientid,jdbcType=INTEGER},
      </if>
    </set>
    <if test="_parameter != null">
      <include refid="Update_By_Example_Where_Clause" />
    </if>
  </update>
  <update id="updateByExample" parameterType="map">
    <!--
      WARNING - @mbg.generated
      This element is automatically generated by MyBatis Generator, do not modify.
      This element was generated on Wed Aug 21 14:57:48 CST 2019.
    -->
    update ownership
    set osid = #{record.osid,jdbcType=INTEGER},
      servicenumber = #{record.servicenumber,jdbcType=VARCHAR},
      roomid = #{record.roomid,jdbcType=INTEGER},
      registertime = #{record.registertime,jdbcType=TIMESTAMP},
      uid = #{record.uid,jdbcType=INTEGER},
      descript = #{record.descript,jdbcType=VARCHAR},
      clientid = #{record.clientid,jdbcType=INTEGER}
    <if test="_parameter != null">
      <include refid="Update_By_Example_Where_Clause" />
    </if>
  </update>
  <update id="updateByPrimaryKeySelective" parameterType="com.woniu.entity.Ownership">
    <!--
      WARNING - @mbg.generated
      This element is automatically generated by MyBatis Generator, do not modify.
      This element was generated on Wed Aug 21 14:57:48 CST 2019.
    -->
    update ownership
    <set>
      <if test="servicenumber != null">
        servicenumber = #{servicenumber,jdbcType=VARCHAR},
      </if>
      <if test="roomid != null">
        roomid = #{roomid,jdbcType=INTEGER},
      </if>
      <if test="registertime != null">
        registertime = #{registertime,jdbcType=TIMESTAMP},
      </if>
      <if test="uid != null">
        uid = #{uid,jdbcType=INTEGER},
      </if>
      <if test="descript != null">
        descript = #{descript,jdbcType=VARCHAR},
      </if>
      <if test="clientid != null">
        clientid = #{clientid,jdbcType=INTEGER},
      </if>
    </set>
    where osid = #{osid,jdbcType=INTEGER}
  </update>
  <update id="updateByPrimaryKey" parameterType="com.woniu.entity.Ownership">
    <!--
      WARNING - @mbg.generated
      This element is automatically generated by MyBatis Generator, do not modify.
      This element was generated on Wed Aug 21 14:57:48 CST 2019.
    -->
    update ownership
    set servicenumber = #{servicenumber,jdbcType=VARCHAR},
      roomid = #{roomid,jdbcType=INTEGER},
      registertime = #{registertime,jdbcType=TIMESTAMP},
      uid = #{uid,jdbcType=INTEGER},
      descript = #{descript,jdbcType=VARCHAR},
      clientid = #{clientid,jdbcType=INTEGER}
    where osid = #{osid,jdbcType=INTEGER}
  </update>
</mapper>